<annotation verified="yes">
	<folder>images</folder>
	<filename>9_5.jpg</filename>
	<path>/content/MaixPy_YoloV2/datasets/sayi/images/9_5.jpg</path>
	<source>
		<database>Unknown</database>
	</source>
	<size>
		<width>169</width>
		<height>225</height>
		<depth>3</depth>
	</size>
	<segmented>0</segmented>
	<object>
		<name>9</name>
		<pose>Unspecified</pose>
		<truncated>0</truncated>
		<difficult>0</difficult>
		<bndbox>
			<xmin>18</xmin>
			<ymin>19</ymin>
			<xmax>144</xmax>
			<ymax>205</ymax>
		</bndbox>
	</object>
</annotation>