<annotation>
	<folder>gesislab</folder>
	<filename>mouse3.jpg</filename>
	<path>/gesislab/mouse3.jpg</path>
	<source>
		<database>Unspecified</database>
	</source>
	<size>
		<width>224</width>
		<height>299</height>
		<depth>3</depth>
	</size>
	<object>
		<name>mouse</name>
		<pose>Unspecified</pose>
		<truncated>Unspecified</truncated>
		<difficult>Unspecified</difficult>
		<bndbox>
			<xmin>64</xmin>
			<ymin>82</ymin>
			<xmax>191</xmax>
			<ymax>185</ymax>
		</bndbox>
	</object>
</annotation>